nfreezer.py
nFreezer-0.0.1.dist-info/LICENSE
nFreezer-0.0.1.dist-info/METADATA
nFreezer-0.0.1.dist-info/WHEEL
nFreezer-0.0.1.dist-info/entry_points.txt
nFreezer-0.0.1.dist-info/top_level.txt
nFreezer-0.0.1.dist-info/RECORD
