Metadata-Version: 2.1
Name: nFreezer
Version: 0.0.1
Summary: nFreezer is an encrypted-at-rest backup tool over SFTP.
Home-page: https://github.com/josephernest/nfreezer
Author: Joseph Ernest
Author-email: nouvellecollection@gmail.com
License: MIT with free-of-charge-redistribution clause
Platform: any
Classifier: Programming Language :: Python :: 3
Classifier: Operating System :: OS Independent
Requires-Python: >=3.6
Requires-Dist: pysftp
Requires-Dist: pycryptodome
